.gitignore
CHANGES.rst
README.rst
setup.py
on/__init__.py
on.zopetools.egg-info/PKG-INFO
on.zopetools.egg-info/SOURCES.txt
on.zopetools.egg-info/dependency_links.txt
on.zopetools.egg-info/entry_points.txt
on.zopetools.egg-info/namespace_packages.txt
on.zopetools.egg-info/not-zip-safe
on.zopetools.egg-info/requires.txt
on.zopetools.egg-info/top_level.txt
on/zopetools/__init__.py
on/zopetools/configure.zcml
on/zopetools/libobjtime.py
on/zopetools/version.txt
on/zopetools/zodbmountpoints.py
on/zopetools/zopestuff.py