Metadata-Version: 1.1
Name: on.zopetools
Version: 0.3
Summary: dynamic display of zopetools files
Home-page: http://www.oeko.net/
Author: Toni Mueller
Author-email: support@oeko.net
License: AGPLv3
Keywords: plone zopetools
Platform: UNKNOWN
Classifier: Framework :: Plone
Classifier: Environment :: Console
Classifier: Programming Language :: Zope
Classifier: Intended Audience :: System Administrators
Classifier: Programming Language :: Python
Classifier: Programming Language :: Zope
Classifier: Topic :: Utilities
